aiboot/__init__.py
aiboot/aiboot.py
aiboot/onboarding.py
aiboot/pack_model.py
aiboot-1.0.7.dist-info/METADATA
aiboot-1.0.7.dist-info/WHEEL
aiboot-1.0.7.dist-info/entry_points.txt
aiboot-1.0.7.dist-info/top_level.txt
aiboot-1.0.7.dist-info/RECORD
