Metadata-Version: 2.1
Name: aiboot
Version: 1.0.7
Summary: CubeAI模型服务化引擎
Home-page: https://github.com/cube-ai/aiboot.git
Author: cubeai
Author-email: cubeai@163.com
License: Apache License 2.0
Keywords: CubeAI machine learning model runner server ml ai
Platform: UNKNOWN
Classifier: Development Status :: 4 - Beta
Classifier: Intended Audience :: Developers
Classifier: Intended Audience :: Science/Research
Classifier: Programming Language :: Python :: 3
Classifier: Programming Language :: Python :: 3.5
Classifier: Programming Language :: Python :: 3.6
Classifier: Programming Language :: Python :: 3.7
Classifier: Programming Language :: Python :: 3.8
Classifier: Programming Language :: Python :: 3.9
Classifier: License :: OSI Approved :: Apache Software License
Requires-Python: >=3.5
Requires-Dist: cython (==0.29.21)
Requires-Dist: requests (==2.24.0)
Requires-Dist: tornado (==6.0.4)
Requires-Dist: pyyaml (==5.3.1)
